{ "backgroundcolor":"#000000",
 "compressionlevel":-1,
 "height":19,
 "infinite":false,
 "layers":[
        {
         "compression":"zlib",
         "data":"eJw7zsDAcHwI4RognkoBrhk1c8iaOZsCPNT9PhjNtBzCZrLhweSaSQgQSp\/oZg52DABl6\/ab",
         "encoding":"base64",
         "height":19,
         "id":1,
         "name":"back",
         "opacity":0.5,
         "type":"tilelayer",
         "visible":true,
         "width":21,
         "x":0,
         "y":0
        }, 
        {
         "compression":"zlib",
         "data":"eJxjYBgFo2DwA3ZGyvFgAIPNPbjAYHFnDwF5kPt6GEhzJyEziVWDrp6NACbVzMEOAIztBEE=",
         "encoding":"base64",
         "height":19,
         "id":2,
         "name":"front",
         "opacity":1,
         "type":"tilelayer",
         "visible":true,
         "width":21,
         "x":0,
         "y":0
        }, 
        {
         "color":"#5555ff",
         "draworder":"topdown",
         "id":3,
         "name":"mods",
         "objects":[],
         "opacity":1,
         "type":"objectgroup",
         "visible":true,
         "x":0,
         "y":0
        }, 
        {
         "color":"#ff0000",
         "draworder":"topdown",
         "id":4,
         "name":"objects",
         "objects":[
                {
                 "gid":2147487047,
                 "height":32,
                 "id":842,
                 "name":"",
                 "rotation":0,
                 "type":"",
                 "visible":true,
                 "width":40,
                 "x":104,
                 "y":136
                }, 
                {
                 "gid":925,
                 "height":32,
                 "id":843,
                 "name":"",
                 "rotation":0,
                 "type":"",
                 "visible":true,
                 "width":32,
                 "x":16,
                 "y":48
                }, 
                {
                 "gid":926,
                 "height":32,
                 "id":844,
                 "name":"",
                 "rotation":0,
                 "type":"",
                 "visible":true,
                 "width":32,
                 "x":120,
                 "y":48
                }, 
                {
                 "gid":3369,
                 "height":24,
                 "id":845,
                 "name":"",
                 "rotation":0,
                 "type":"",
                 "visible":true,
                 "width":40,
                 "x":24,
                 "y":128
                }, 
                {
                 "gid":3432,
                 "height":16,
                 "id":850,
                 "name":"",
                 "rotation":0,
                 "type":"",
                 "visible":true,
                 "width":48,
                 "x":104,
                 "y":64
                }, 
                {
                 "gid":2147487091,
                 "height":16,
                 "id":852,
                 "name":"",
                 "rotation":0,
                 "type":"",
                 "visible":true,
                 "width":24,
                 "x":32,
                 "y":64
                }, 
                {
                 "gid":2147487091,
                 "height":16,
                 "id":853,
                 "name":"",
                 "rotation":0,
                 "type":"",
                 "visible":true,
                 "width":24,
                 "x":56,
                 "y":64
                }, 
                {
                 "gid":2147487091,
                 "height":16,
                 "id":854,
                 "name":"",
                 "rotation":0,
                 "type":"",
                 "visible":true,
                 "width":24,
                 "x":40,
                 "y":48
                }, 
                {
                 "gid":8998,
                 "height":16,
                 "id":856,
                 "name":"",
                 "rotation":0,
                 "type":"",
                 "visible":true,
                 "width":16,
                 "x":16,
                 "y":64
                }, 
                {
                 "gid":2147489855,
                 "height":22,
                 "id":857,
                 "name":"",
                 "rotation":0,
                 "type":"",
                 "visible":true,
                 "width":8,
                 "x":88,
                 "y":64
                }, 
                {
                 "gid":5062,
                 "height":16,
                 "id":858,
                 "name":"",
                 "rotation":0,
                 "type":"",
                 "visible":true,
                 "width":16,
                 "x":96,
                 "y":40
                }],
         "opacity":1,
         "type":"objectgroup",
         "visible":true,
         "x":0,
         "y":0
        }, 
        {
         "color":"#ffff00",
         "draworder":"topdown",
         "id":5,
         "name":"wiring - lights & guns",
         "objects":[],
         "opacity":1,
         "type":"objectgroup",
         "visible":true,
         "x":0,
         "y":0
        }, 
        {
         "color":"#ff0000",
         "draworder":"topdown",
         "id":6,
         "name":"monsters & npcs",
         "objects":[
                {
                 "height":8,
                 "id":846,
                 "name":"Fluffalo",
                 "properties":[
                        {
                         "name":"monster",
                         "type":"string",
                         "value":"fluffalo"
                        }],
                 "rotation":0,
                 "type":"",
                 "visible":true,
                 "width":8,
                 "x":56,
                 "y":104
                }],
         "opacity":1,
         "type":"objectgroup",
         "visible":true,
         "x":0,
         "y":0
        }, 
        {
         "color":"#00ffff",
         "draworder":"topdown",
         "id":7,
         "name":"wiring - locked door",
         "objects":[],
         "opacity":1,
         "type":"objectgroup",
         "visible":true,
         "x":0,
         "y":0
        }, 
        {
         "draworder":"topdown",
         "id":8,
         "name":"outside the map",
         "objects":[],
         "opacity":1,
         "type":"objectgroup",
         "visible":true,
         "x":0,
         "y":0
        }, 
        {
         "draworder":"topdown",
         "id":9,
         "name":"anchors etc",
         "objects":[
                {
                 "gid":211,
                 "height":8,
                 "id":841,
                 "name":"STAIRWELL STORAGE LEFT",
                 "properties":[
                        {
                         "name":"connector",
                         "type":"string",
                         "value":"255,255,255,255"
                        }],
                 "rotation":0,
                 "type":"",
                 "visible":true,
                 "width":8,
                 "x":160,
                 "y":120
                }, 
                {
                 "height":120,
                 "id":864,
                 "name":"",
                 "properties":[
                        {
                         "name":"stagehand",
                         "type":"string",
                         "value":"objecttracker"
                        }],
                 "rotation":0,
                 "type":"",
                 "visible":true,
                 "width":136,
                 "x":16,
                 "y":16
                }],
         "opacity":1,
         "type":"objectgroup",
         "visible":true,
         "x":0,
         "y":0
        }, 
        {
         "draworder":"topdown",
         "id":10,
         "name":"items",
         "objects":[],
         "opacity":1,
         "type":"objectgroup",
         "visible":true,
         "x":0,
         "y":0
        }],
 "nextlayerid":11,
 "nextobjectid":865,
 "orientation":"orthogonal",
 "renderorder":"right-down",
 "tiledversion":"1.10.0",
 "tileheight":8,
 "tilesets":[
        {
         "firstgid":1,
         "source":"..\/..\/..\/..\/tilesets\/packed\/materials.json"
        }, 
        {
         "firstgid":198,
         "source":"..\/..\/..\/..\/tilesets\/packed\/miscellaneous.json"
        }, 
        {
         "firstgid":222,
         "source":"..\/..\/..\/..\/tilesets\/packed\/liquids.json"
        }, 
        {
         "firstgid":250,
         "source":"..\/..\/..\/..\/tilesets\/packed\/supports.json"
        }, 
        {
         "firstgid":287,
         "source":"..\/..\/..\/..\/tilesets\/packed\/objects-by-race\/generic.json"
        }, 
        {
         "firstgid":2271,
         "source":"..\/..\/..\/..\/tilesets\/packed\/objects-by-race\/ancient.json"
        }, 
        {
         "firstgid":2434,
         "source":"..\/..\/..\/..\/tilesets\/packed\/objects-by-race\/apex.json"
        }, 
        {
         "firstgid":2805,
         "source":"..\/..\/..\/..\/tilesets\/packed\/objects-by-race\/avian.json"
        }, 
        {
         "firstgid":3110,
         "source":"..\/..\/..\/..\/tilesets\/packed\/objects-by-race\/floran.json"
        }, 
        {
         "firstgid":3305,
         "source":"..\/..\/..\/..\/tilesets\/packed\/objects-by-race\/glitch.json"
        }, 
        {
         "firstgid":3531,
         "source":"..\/..\/..\/..\/tilesets\/packed\/objects-by-race\/human.json"
        }, 
        {
         "firstgid":3819,
         "source":"..\/..\/..\/..\/tilesets\/packed\/objects-by-race\/hylotl.json"
        }, 
        {
         "firstgid":4051,
         "source":"..\/..\/..\/..\/tilesets\/packed\/objects-by-race\/novakid.json"
        }, 
        {
         "firstgid":4115,
         "source":"..\/..\/..\/..\/tilesets\/packed\/objects-by-category\/crafting.json"
        }, 
        {
         "firstgid":4195,
         "source":"..\/..\/..\/..\/tilesets\/packed\/objects-by-category\/decorative.json"
        }, 
        {
         "firstgid":5636,
         "source":"..\/..\/..\/..\/tilesets\/packed\/objects-by-category\/door.json"
        }, 
        {
         "firstgid":5768,
         "source":"..\/..\/..\/..\/tilesets\/packed\/objects-by-category\/farmable.json"
        }, 
        {
         "firstgid":5843,
         "source":"..\/..\/..\/..\/tilesets\/packed\/objects-by-category\/furniture.json"
        }, 
        {
         "firstgid":6197,
         "source":"..\/..\/..\/..\/tilesets\/packed\/objects-by-category\/light.json"
        }, 
        {
         "firstgid":6655,
         "source":"..\/..\/..\/..\/tilesets\/packed\/objects-by-category\/other.json"
        }, 
        {
         "firstgid":6967,
         "source":"..\/..\/..\/..\/tilesets\/packed\/objects-by-category\/pot.json"
        },
    
        {
         "firstgid":7264,
         "source":"..\/..\/..\/..\/tilesets\/packed\/objects-by-category\/sapling.json"
        }, 
        {
         "firstgid":7265,
         "source":"..\/..\/..\/..\/tilesets\/packed\/objects-by-category\/spawner.json"
        }, 
        {
         "firstgid":7281,
         "source":"..\/..\/..\/..\/tilesets\/packed\/objects-by-category\/storage.json"
        }, 
        {
         "firstgid":7515,
         "source":"..\/..\/..\/..\/tilesets\/packed\/objects-by-category\/teleporter.json"
        }, 
        {
         "firstgid":7557,
         "source":"..\/..\/..\/..\/tilesets\/packed\/objects-by-category\/tools.json"
        }, 
        {
         "firstgid":7562,
         "source":"..\/..\/..\/..\/tilesets\/packed\/objects-by-category\/trap.json"
        }, 
        {
         "firstgid":7766,
         "source":"..\/..\/..\/..\/tilesets\/packed\/objects-by-category\/wire.json"
        }, 
        {
         "firstgid":7988,
         "source":"..\/..\/..\/..\/tilesets\/packed\/objects-by-type\/container.json"
        }, 
        {
         "firstgid":8273,
         "source":"..\/..\/..\/..\/tilesets\/packed\/objects-by-type\/farmable.json"
        }, 
        {
         "firstgid":8351,
         "source":"..\/..\/..\/..\/tilesets\/packed\/objects-by-type\/loungeable.json"
        }, 
        {
         "firstgid":8632,
         "source":"..\/..\/..\/..\/tilesets\/packed\/objects-by-type\/noisy.json"
        }, 
        {
         "firstgid":8673,
         "source":"..\/..\/..\/..\/tilesets\/packed\/objects-by-type\/teleporter.json"
        }, 
        {
         "firstgid":8700,
         "source":"..\/..\/..\/..\/tilesets\/packed\/huge-objects.json"
        }, 
        {
         "firstgid":8801,
         "source":"..\/..\/..\/..\/tilesets\/packed\/objects-by-category\/breakable.json"
        }, 
        {
         "firstgid":9111,
         "source":"..\/..\/..\/..\/tilesets\/packed\/objects-by-colonytag\/mining.json"
        }],
 "tilewidth":8,
 "type":"map",
 "version":"1.10",
 "width":21
}